ovos_i2c_detection/__init__.py
ovos_i2c_detection/version.py
ovos_i2c_detection-0.0.5.dist-info/LICENSE
ovos_i2c_detection-0.0.5.dist-info/METADATA
ovos_i2c_detection-0.0.5.dist-info/WHEEL
ovos_i2c_detection-0.0.5.dist-info/top_level.txt
ovos_i2c_detection-0.0.5.dist-info/RECORD
