Metadata-Version: 2.1
Name: ovos-i2c-detection
Version: 0.0.5
Summary: i2c detection for some devices
Home-page: https://github.com/OpenVoiceOS/ovos_i2c_detection
Author: builderjer
Author-email: builderjer@gmail.com
License: MIT
License-File: LICENSE
Requires-Dist: pyserial
